aio_straico/__init__.py
aio_straico/async_client.py
aio_straico/async_client_agent.py
aio_straico/async_client_rag.py
aio_straico/client.py
aio_straico/client_agent.py
aio_straico/client_rag.py
aio_straico/straico_requests.py
aio_straico/api/__init__.py
aio_straico/api/smartllmselector.py
aio_straico/api/v0.py
aio_straico/api/v0_agent.py
aio_straico/api/v0_rag.py
aio_straico/api/v1.py
aio_straico/api/v1_image_to_video.py
aio_straico/api/v1_tts.py
aio_straico/utils/__init__.py
aio_straico/utils/asset_utils.py
aio_straico/utils/model_features.py
aio_straico/utils/models.py
aio_straico/utils/models_to_enum.py
aio_straico/utils/tracing.py
aio_straico/utils/transcript_utils.py
aio_straico-0.3.0.dist-info/licenses/LICENSE
tests/__init__.py
tests/test_async_client.py
tests/test_client.py
tests/test_rag.py
tests/test_upload_file.py
tests/utils/__init__.py
aio_straico-0.3.0.dist-info/METADATA
aio_straico-0.3.0.dist-info/WHEEL
aio_straico-0.3.0.dist-info/top_level.txt
aio_straico-0.3.0.dist-info/RECORD
