Metadata-Version: 2.4
Name: aio_straico
Version: 0.3.0
Summary: An unofficial async/sync client library for Straico API
Home-page: https://github.com/jayrinaldime/aio-straico
Author: Jay Rinaldi
Author-email: jrinaldi@jayrinaldi.me
Project-URL: Source, https://github.com/jayrinaldime/aio-straico
Project-URL: Documentation, https://github.com/jayrinaldime/aio-straico?tab=readme-ov-file#readme
Classifier: Intended Audience :: Developers
Classifier: License :: Freely Distributable
Classifier: License :: OSI Approved :: MIT License
Classifier: Programming Language :: Python :: 3.9
Classifier: Programming Language :: Python :: 3.10
Classifier: Programming Language :: Python :: 3.11
Classifier: Programming Language :: Python :: 3.12
Classifier: Programming Language :: Python :: 3.13
Classifier: Programming Language :: Python :: 3 :: Only
Classifier: Programming Language :: Python
Classifier: Programming Language :: Python :: Implementation :: CPython
Classifier: Topic :: Communications :: Chat
Classifier: Topic :: Adaptive Technologies
Classifier: Development Status :: 4 - Beta
Classifier: Operating System :: OS Independent
Classifier: Operating System :: POSIX :: Linux
Classifier: Operating System :: MacOS
Classifier: Operating System :: Microsoft :: Windows
Requires-Python: >=3.9,<=3.13
License-File: LICENSE
Requires-Dist: httpx>=0.28.0
Dynamic: author
Dynamic: author-email
Dynamic: classifier
Dynamic: description
Dynamic: description-content-type
Dynamic: home-page
Dynamic: license-file
Dynamic: project-url
Dynamic: requires-dist
Dynamic: requires-python
Dynamic: summary
